chemfusekit/__init__.py
chemfusekit/_base.py
chemfusekit/_utils.py
chemfusekit/df.py
chemfusekit/knn.py
chemfusekit/lda.py
chemfusekit/lr.py
chemfusekit/pca.py
chemfusekit/plsda.py
chemfusekit/svm.py
chemfusekit-3.1.0.dist-info/METADATA
chemfusekit-3.1.0.dist-info/WHEEL
chemfusekit-3.1.0.dist-info/licenses/LICENSE
chemfusekit-3.1.0.dist-info/RECORD
