Metadata-Version: 2.3
Name: chemfusekit
Version: 3.1.0
Summary: A minimal Python / Jupyter Notebook / Colab library for data fusion and chemometrical analysis.
Author-email: Federico Aguzzi <62149513+f-aguzzi@users.noreply.github.com>
License-File: LICENSE
Requires-Python: >=3.10
Requires-Dist: beartype>=0.18.5
Requires-Dist: matplotlib>=3.8.4
Requires-Dist: nbformat>=4.2.0
Requires-Dist: numpy==2.0.0
Requires-Dist: openpyxl>=3.1.2
Requires-Dist: pandas==2.2.2
Requires-Dist: plotly>=5.22.0
Requires-Dist: scikit-learn>=1.4.2
Requires-Dist: scipy>=1.13.0
Requires-Dist: seaborn>=0.13.2
Requires-Dist: tabulate>=0.9.0
